excitationsolve/__init__.py
excitationsolve/excitation_solve.py
excitationsolve/excitation_solve_2d.py
excitationsolve/excitation_solve_adapt.py
excitationsolve/excitation_solve_pennylane.py
excitationsolve/excitation_solve_qiskit.py
excitationsolve/excitation_solve_scipy.py
excitationsolve/info.py
excitationsolve/trig_poly_utils.py
excitationsolve-2.1.2.dist-info/licenses/LICENSE.txt
excitationsolve-2.1.2.dist-info/METADATA
excitationsolve-2.1.2.dist-info/WHEEL
excitationsolve-2.1.2.dist-info/top_level.txt
excitationsolve-2.1.2.dist-info/RECORD
