Metadata-Version: 2.4
Name: excitationsolve
Version: 2.1.2
Summary: ExcitationSolve: a fast globally-informed gradient-free optimizer for physically-motivated ansätze constructed of excitation operators
Author-email: Jonas Jäger <jojaeger@cs.ubc.ca>, "Thierry N. Kaldenbach" <Thierry.Kaldenbach@dlr.de>, Max Haas <Max.Haas@dlr.de>, Erik Schultheis <Erik.Schultheis@dlr.de>
License:        Copyright 2025 Jonas Jäger, Thierry N. Kaldenbach, Max Haas, Erik Schultheis,
Project-URL: Repository, https://github.com/dlr-wf/ExcitationSolve/
Project-URL: Issues, https://github.com/dlr-wf/ExcitationSolve/issues
Keywords: optimizer,quantum computing,ExcitationSolve,gradient-free,excitation operators,UCCSD,VQE
Classifier: Intended Audience :: Science/Research
Classifier: Programming Language :: Python :: 3
Classifier: Programming Language :: Python :: 3.8
Classifier: Programming Language :: Python :: 3.9
Classifier: Programming Language :: Python :: 3.10
Classifier: Programming Language :: Python :: 3.11
Requires-Python: >=3.8
License-File: LICENSE.txt
Requires-Dist: numpy
Requires-Dist: scipy
Provides-Extra: examples
Requires-Dist: qiskit==1.4.0; extra == "examples"
Requires-Dist: qiskit-algorithms==0.3.1; extra == "examples"
Requires-Dist: qiskit-nature==0.7.2; extra == "examples"
Requires-Dist: pyscf==2.8.0; extra == "examples"
Requires-Dist: pennylane==0.42.3; extra == "examples"
Requires-Dist: openfermionpyscf==0.5; extra == "examples"
Requires-Dist: aiohttp==3.11.15; extra == "examples"
Requires-Dist: fsspec==2025.2.0; extra == "examples"
Requires-Dist: h5py==3.13.0; extra == "examples"
Dynamic: license-file
